{
  "tabs": [
    {
      "identifier": "offers",
      "rows": [
        {
          "cols": [
            {
              "span": 12,
              "components": [
                {
                  "type": "headline",
                  "options": {
                    "identifier": "general",
                    "icon": "user"
                  }
                },
                {
                  "type": "field_group",
                  "options": {
                    "vertical_labels": false,
                    "fields": [
                      "process",
                      "date",
                      "created_by",
                      "customer",
                      "object",
                      "problem"
                    ]
                  }
                }
              ]
            },
            {
              "span": 12,
              "components": [
                {
                  "type": "headline",
                  "options": {
                    "identifier": "info",
                    "icon": "user"
                  }
                },
                {
                  "type": "field_group",
                  "options": {
                    "vertical_labels": false,
                    "fields": [
                      "room_temperature",
                      "room_humidity",
                      "surface_temperature",
                      "construction_year",
                      "wall_material",
                      "wall_thickness",
                      "building_type",
                      "level",
                      "floor_material",
                      "strip_foundation",
                      "seals_done_in_the_past",
                      "pdf_info_text"
                    ]
                  }
                }
              ]
            }
          ]
        },
        {
          "cols": [
            {
              "components": [
                {
                  "type": "headline",
                  "options": {
                    "identifier": "positions"
                  }
                },
                {
                  "options": {
                    "no_labels": true,
                    "fields": ["positions"]
                  },
                  "type": "field_group"
                }
              ],
              "span": 24
            }
          ]
        },
        {
          "cols": [
            {
              "components": [
                {
                  "options": {
                    "fields": []
                  },
                  "type": "field_group"
                }
              ],
              "span": 12
            },
            {
              "components": [
                {
                  "options": {
                    "vertical_labels": false,
                    "fields": ["overall_discount", "price_net", "taxrate", "tax_amount", "price_total"]
                  },
                  "type": "field_group"
                }
              ],
              "span": 12
            }
          ]
        }
      ]
    }
  ]
}
